lumi_cua_sdk_test/__about__.py
lumi_cua_sdk_test/__init__.py
lumi_cua_sdk_test/client.py
lumi_cua_sdk_test/main.py
lumi_cua_sdk_test/sandbox.py
lumi_cua_sdk_test/agent/__init__.py
lumi_cua_sdk_test/agent/tools.py
lumi_cua_sdk_test/models/common.py
lumi_cua_sdk_test/models/cua_uitars_agent_models.py
lumi_cua_sdk_test/models/tool_server_models.py
lumi_cua_sdk_test/services/cua_uitars_agent.py
lumi_cua_sdk_test/services/ecs_manager_client.py
lumi_cua_sdk_test/services/tool_server_client.py
lumi_cua_sdk_test-1.0.0.dist-info/METADATA
lumi_cua_sdk_test-1.0.0.dist-info/WHEEL
lumi_cua_sdk_test-1.0.0.dist-info/licenses/LICENSE
lumi_cua_sdk_test-1.0.0.dist-info/RECORD
