Metadata-Version: 2.4
Name: lumi_cua_sdk_test
Version: 1.0.0
Summary: This is the Python SDK for Computer Use Tool Server, allowing you to easily control the computer desktop environment from your applications.
Project-URL: Documentation, https://github.com/lvlv/tool-server-client#readme
Project-URL: Issues, https://github.com/lvlv/tool-server-client/issues
Project-URL: Source, https://github.com/lvlv/tool-server-client
Author-email: lvlv <lvgj1998@gmail.com>
License-Expression: MIT
License-File: LICENSE
Classifier: Development Status :: 4 - Beta
Classifier: Programming Language :: Python
Classifier: Programming Language :: Python :: 3.12
Classifier: Programming Language :: Python :: Implementation :: CPython
Classifier: Programming Language :: Python :: Implementation :: PyPy
Requires-Python: >=3.12
Requires-Dist: jinja2>=3.1.6
Requires-Dist: langchain-core>=0.3.58
Requires-Dist: langchain-openai>=0.3.16
Requires-Dist: langgraph>=0.4.1
Requires-Dist: mcp>=1.7.1
Requires-Dist: openai>=1.72.0
Requires-Dist: pydantic>=1.8.0
Requires-Dist: requests>=2.25.0
